document_forger/__init__.py
document_forger/__main__.py
document_forger/document_processing.py
document_forger/image_processing.py
document_forger/ocr.py
document_forger/suppress_output.py
document_forger/utils.py
document_forger-1.1.1.dist-info/LICENSE
document_forger-1.1.1.dist-info/METADATA
document_forger-1.1.1.dist-info/WHEEL
document_forger-1.1.1.dist-info/entry_points.txt
document_forger-1.1.1.dist-info/top_level.txt
document_forger-1.1.1.dist-info/RECORD
