Metadata-Version: 2.1
Name: document-forger
Version: 1.1.1
Summary: A package for generating forged documents
Home-page: https://github.com/visionrd-ai/document-forger.git
Classifier: Programming Language :: Python :: 3
Classifier: License :: OSI Approved :: MIT License
Classifier: Operating System :: OS Independent
Requires-Python: >=3.8
License-File: LICENSE
Requires-Dist: opencv-python >=4.5.1
Requires-Dist: pytesseract >=0.3.7
Requires-Dist: pillow >=8.1.0
Requires-Dist: pandas >=1.2.3
Requires-Dist: tqdm >=4.59.0
Requires-Dist: numpy >=1.20.1
Requires-Dist: torch >=2.3.1
Requires-Dist: torchvision >=0.18.1
Requires-Dist: super-image >=0.1.7
